mesa_reader/__init__.py
mesa_reader-0.3.5.dist-info/METADATA
mesa_reader-0.3.5.dist-info/WHEEL
mesa_reader-0.3.5.dist-info/top_level.txt
mesa_reader-0.3.5.dist-info/RECORD
