Metadata-Version: 2.1
Name: mesa-reader
Version: 0.3.5
Summary: Tools for interacting with output from MESA star and MESA binary
Home-page: http://github.com/wmwolf/py_mesa_reader
Author: William M. Wolf
Author-email: wolfwm@uwec.edu
License: MIT
Classifier: Programming Language :: Python :: 3
Classifier: License :: OSI Approved :: MIT License
Classifier: Operating System :: OS Independent
Requires-Python: >=3.6
Requires-Dist: numpy
